laforge/__init__.py
laforge/__main__.py
laforge/builder.py
laforge/command.py
laforge/create_ini.py
laforge/distros.py
laforge/logo.py
laforge/sql.py
laforge/tech.py
laforge/tech_inputs.txt
laforge/toolbox.py
test/__init__.py
test/__test_sql_revamp.py
test/conftest.py
test/fix_sqlite.py
test/secret_config.py
test/test_broken_builds.py
test/test_builder_Task.py
test/test_command.py
test/test_csv_sample_watch.py
test/test_save_cfg.py
test/test_sql_Channel.py
test/test_sql_Distro.py
test/test_sql_Identifier.py
test/test_sql_Script.py
test/test_sql_Table.py
test/test_sql_execute.py
test/test_toolbox.py
laforge-0.1.6.dist-info/LICENSE
laforge-0.1.6.dist-info/METADATA
laforge-0.1.6.dist-info/WHEEL
laforge-0.1.6.dist-info/entry_points.txt
laforge-0.1.6.dist-info/top_level.txt
laforge-0.1.6.dist-info/RECORD
